LICENSE
MANIFEST.in
README.rst
setup.cfg
setup.py
gitsuggest/__init__.py
gitsuggest/commandline.py
gitsuggest/suggest.py
gitsuggest/utilities.py
gitsuggest.egg-info/PKG-INFO
gitsuggest.egg-info/SOURCES.txt
gitsuggest.egg-info/dependency_links.txt
gitsuggest.egg-info/entry_points.txt
gitsuggest.egg-info/requires.txt
gitsuggest.egg-info/top_level.txt
gitsuggest/gitlang/languages.txt
gitsuggest/gitlang/others.txt
gitsuggest/res/base.htm.j2
gitsuggest/res/logo.png
gitsuggest/res/page.template
gitsuggest/res/result.template
gitsuggest/res/suggest.htm.j2
tests/__init__.py
tests/mockentities.py
tests/test_suggest.py
tests/test_utilities.py