Metadata-Version: 1.1
Name: gitsuggest
Version: 0.0.13
Summary: A tool to suggest github repositories based on the repositories you have shown interest in.
Home-page: https://github.com/csurfer/gitsuggest
Author: Vishwas B Sharma
Author-email: sharma.vishwas88@gmail.com
License: MIT
Keywords: github repository suggestion
Platform: UNKNOWN
Classifier: Intended Audience :: Developers
Classifier: Intended Audience :: Education
Classifier: License :: OSI Approved :: MIT License
Classifier: Development Status :: 3 - Alpha
Classifier: Operating System :: POSIX
Classifier: Programming Language :: Python :: 2.7
Classifier: Programming Language :: Python :: 3.4
Classifier: Programming Language :: Python :: 3.5
Classifier: Programming Language :: Python :: 3.6
Classifier: Topic :: Software Development :: Libraries :: Python Modules
